groundwater_tools/__init__.py
groundwater_tools/pitflow.py
groundwater_tools-0.2.1.dist-info/WHEEL
groundwater_tools-0.2.1.dist-info/METADATA
groundwater_tools-0.2.1.dist-info/RECORD
