Metadata-Version: 2.3
Name: groundwater-tools
Version: 0.2.1
Summary: Library for processing groundwater data and constructing simple analytical models.
Author: Kaarel Mänd
Author-email: Kaarel Mänd <kaarel.mand@protonmail.com>
License: MIT
Classifier: Intended Audience :: Science/Research
Classifier: License :: OSI Approved :: MIT License
Classifier: Programming Language :: Python :: 3
Classifier: Topic :: Scientific/Engineering :: Hydrology
Requires-Dist: matplotlib>=3.10.5
Requires-Dist: pandas>=2.3.1
Requires-Dist: scipy>=1.16.1
Requires-Python: >=3.12
Project-URL: Homepage, https://github.com/kaarelmand/groundwater_tools
